ftk/PRIVACY.txt
ftk/VERSION.txt
ftk/__init__.py
ftk/base_estimator.py
ftk/constants.py
ftk/dnn_utils.py
ftk/exception.py
ftk/factor_types.py
ftk/forecast_data_frame.py
ftk/inspect_exceptions.py
ftk/multi_forecast_data_frame.py
ftk/non_parametric_distribution.py
ftk/pipeline.py
ftk/string_exceptions.py
ftk/time_series_data_frame.py
ftk/time_series_logging.py
ftk/transform_utils.py
ftk/ts_utils.py
ftk/utils.py
ftk/verify.py
ftk/compute/__init__.py
ftk/compute/aml_compute.py
ftk/compute/compute_base.py
ftk/compute/experiment.py
ftk/compute/scale_out_compute.py
ftk/compute/scale_up_compute.py
ftk/compute/scheduler.py
ftk/data/__init__.py
ftk/data/FRED/UNRATE.csv
ftk/data/FRED/__init__.py
ftk/data/dominicks_oj/__init__.py
ftk/data/dominicks_oj/dominicks_oj.csv
ftk/data/dominicks_oj/dominicks_oj_features.csv
ftk/data/dominicks_oj/load_dominicks_oj_data.py
ftk/data/dow_jones/__init__.py
ftk/data/dow_jones/dow_jones_data.tsv
ftk/data/dow_jones/load_dow_jones_data.py
ftk/data/hyndman/README.md
ftk/data/hyndman/__init__.py
ftk/data/hyndman/quarterly-beer-production-in-aus.csv
ftk/data/surface_sales/README.md
ftk/data/surface_sales/__init__.py
ftk/data/surface_sales/load_surface_data.py
ftk/data/surface_sales/surface_sales_sample.csv
ftk/data/weather/__init__.py
ftk/data/weather/isd-history.csv
ftk/data/weather/load_noaa_weather_data.py
ftk/datasources/__init__.py
ftk/datasources/data_transformer_mixin.py
ftk/datasources/forecast_blob_data_sink.py
ftk/datasources/forecast_blob_data_source.py
ftk/datasources/forecast_data_sink.py
ftk/datasources/forecast_data_source.py
ftk/datasources/forecast_sql_data_sink.py
ftk/datasources/forecast_sql_data_source.py
ftk/datasources/sql_data_manager.py
ftk/metrics/__init__.py
ftk/metrics/metrics.py
ftk/metrics/scorer.py
ftk/model_selection/__init__.py
ftk/model_selection/cross_validation.py
ftk/model_selection/search.py
ftk/models/__init__.py
ftk/models/arima.py
ftk/models/best_of_forecaster.py
ftk/models/exponential_smoothing.py
azuremlftk-0.1.19032.1.dist-info/LICENSE.txt
azuremlftk-0.1.19032.1.dist-info/METADATA
azuremlftk-0.1.19032.1.dist-info/WHEEL
azuremlftk-0.1.19032.1.dist-info/top_level.txt
azuremlftk-0.1.19032.1.dist-info/RECORD
